aiomoqt/__init__.py
aiomoqt/client.py
aiomoqt/context.py
aiomoqt/protocol.py
aiomoqt/server.py
aiomoqt/types.py
aiomoqt/examples/join_example.py
aiomoqt/examples/pub_example.py
aiomoqt/examples/server_example.py
aiomoqt/examples/sub_example.py
aiomoqt/messages/__init__.py
aiomoqt/messages/announce.py
aiomoqt/messages/base.py
aiomoqt/messages/fetch.py
aiomoqt/messages/setup.py
aiomoqt/messages/subscribe.py
aiomoqt/messages/track.py
aiomoqt/tests/conftest.py
aiomoqt/tests/test_messages.py
aiomoqt/tests/test_moqt.py
aiomoqt/tests/test_protocol.py
aiomoqt/utils/__init__.py
aiomoqt/utils/logger.py
aiomoqt-0.3.9.dist-info/LICENSE
aiomoqt-0.3.9.dist-info/METADATA
aiomoqt-0.3.9.dist-info/WHEEL
aiomoqt-0.3.9.dist-info/top_level.txt
aiomoqt-0.3.9.dist-info/RECORD
