Metadata-Version: 2.2
Name: aiomoqt
Version: 0.3.9
Summary: Python asyncio implementation of the MoQT protocol
Author-email: Giovanni Marzot <gmarzot@marzresearch.net>
License: MIT
Project-URL: Homepage, https://github.com/gmarzot/aiomoqt-python
Project-URL: Repository, https://github.com/gmarzot/aiomoqt-python.git
Requires-Python: >=3.10
License-File: LICENSE
Requires-Dist: asyncio>=3.4.3
Requires-Dist: aioquic>=1.2.0
Provides-Extra: test
Requires-Dist: pytest; extra == "test"
Provides-Extra: examples
Requires-Dist: argparse; extra == "examples"
